wchk/__about__.py
wchk/__init__.py
wchk/cli.py
wchk-0.1.0.dist-info/METADATA
wchk-0.1.0.dist-info/WHEEL
wchk-0.1.0.dist-info/entry_points.txt
wchk-0.1.0.dist-info/licenses/LICENSE
wchk-0.1.0.dist-info/RECORD
