Metadata-Version: 2.1
Name: wchk
Version: 0.1.0
Summary: A command line tool to check the status web pages.
Project-URL: CI, https://github.com/yaph/wchk/actions
Project-URL: Changelog, https://github.com/yaph/wchk/releases
Project-URL: Homepage, https://github.com/yaph/wchk
Project-URL: Issues, https://github.com/yaph/wchk/issues
Author-email: Ramiro Gómez <code@ramiro.org>
License-File: LICENSE
Keywords: http,status,webpagecheck,webpagetest
Requires-Python: >=3.7
Requires-Dist: httpx
Requires-Dist: rich
